enum_actions/__init__.py
enum_actions/py.typed
enum_actions-0.1.2.dist-info/WHEEL
enum_actions-0.1.2.dist-info/METADATA
enum_actions-0.1.2.dist-info/RECORD
