Metadata-Version: 2.1
Name: enum-actions
Version: 0.1.2
Summary: For easy selection command-line selection of an `enum.Enum` variant with `argparse.Action`s.
Home-page: https://github.com/aatifsyed/enum-actions
Author: Aatif Syed
Author-email: aatifsyedyp@gmail.com
Requires-Python: >=3.6.2,<4.0.0
Classifier: Programming Language :: Python :: 3
Classifier: Programming Language :: Python :: 3.10
Classifier: Programming Language :: Python :: 3.7
Classifier: Programming Language :: Python :: 3.8
Classifier: Programming Language :: Python :: 3.9
Project-URL: Repository, https://github.com/aatifsyed/enum-actions
